README.rst
setup.py
cyberpot/__init__.py
cyberpot/__main__.py
cyberpot.egg-info/PKG-INFO
cyberpot.egg-info/SOURCES.txt
cyberpot.egg-info/dependency_links.txt
cyberpot.egg-info/not-zip-safe
cyberpot.egg-info/top_level.txt