Metadata-Version: 2.1
Name: cyberpot
Version: 1.0.0
Summary: Simple TCP honeypot
License: UNKNOWN
Platform: UNKNOWN
